{
  "name": "t:sections.footer.name",
  "type": "footer",
  "sections": {
    "footer": {
      "type": "footer",
      "blocks": {
        "footer-0": {
          "type": "link_list",
          "settings": {
            "heading": "Community",
            "menu": "community"
          }
        },
        "link_list_mHULaK": {
          "type": "link_list",
          "settings": {
            "heading": "Shop",
            "menu": "shop"
          }
        },
        "footer-1": {
          "type": "link_list",
          "settings": {
            "heading": "Service",
            "menu": "service"
          }
        },
        "link_list_t746YK": {
          "type": "link_list",
          "settings": {
            "heading": "CHUCK",
            "menu": "service"
          }
        }
      },
      "block_order": [
        "footer-0",
        "link_list_mHULaK",
        "footer-1",
        "link_list_t746YK"
      ],
      "settings": {
        "color_scheme": "scheme-1",
        "newsletter_enable": true,
        "newsletter_heading": "Subscribe to our emails",
        "enable_follow_on_shop": true,
        "show_social": true,
        "enable_country_selector": false,
        "enable_language_selector": false,
        "payment_enable": true,
        "show_policy": true,
        "margin_top": 120,
        "padding_top": 80,
        "padding_bottom": 80
      }
    }
  },
  "order": [
    "footer"
  ]
}
